ungoliant/__init__.py
ungoliant/cli.py
ungoliant-0.1.2.dist-info/entry_points.txt
ungoliant-0.1.2.dist-info/WHEEL
ungoliant-0.1.2.dist-info/METADATA
ungoliant-0.1.2.dist-info/RECORD
